relucent/README.md
relucent/__init__.py
relucent/complex.py
relucent/convert_model.py
relucent/model.py
relucent/poly.py
relucent/ss.py
relucent/utils.py
relucent-0.3.0.dist-info/WHEEL
relucent-0.3.0.dist-info/METADATA
relucent-0.3.0.dist-info/RECORD
