Metadata-Version: 2.4
Name: relucent
Version: 0.3.0
Summary: Explore the polyhedral complexes of ReLU neural networks.
Author: Blake B. Gaines
License-Expression: AGPL-3.0-or-later
Requires-Dist: pandas>=2.3
Requires-Dist: gurobipy>=12.0
Requires-Dist: networkx>=3.6
Requires-Dist: matplotlib>=3.10
Requires-Dist: numpy>=2.4
Requires-Dist: pillow>=12.1
Requires-Dist: plotly>=6.3
Requires-Dist: scikit-learn>=1.8
Requires-Dist: scipy>=1.17
Requires-Dist: tqdm>=4.67
Requires-Dist: torch>=2.13 ; extra == 'cli'
Requires-Dist: torchvision ; extra == 'cli'
Requires-Dist: pyvis>=0.3 ; extra == 'cli'
Requires-Dist: kaleido ; extra == 'cli'
Requires-Python: >=3.13, <3.14
Project-URL: Repository, https://github.com/bl-ake/relucent
Project-URL: Documentation, https://bl-ake.github.io/relucent/
Provides-Extra: cli
